imagemap/__init__.py
imagemap-0.0.0.dist-info/METADATA
imagemap-0.0.0.dist-info/WHEEL
imagemap-0.0.0.dist-info/top_level.txt
imagemap-0.0.0.dist-info/RECORD
