Metadata-Version: 2.1
Name: imagemap
Version: 0.0.0
Summary: imagemap
Home-page: https://github.com/njanakiev/imagemap.git
Author: Author Name
Author-email: nikolai.janakiev@gmail.com
License: UNKNOWN
Platform: any
